{
  "scope": "sermon",
  "idf_scope": "church",
  "church": "O-mQ",
  "sermon": "O-mQ-0115",
  "document_unit": "sermon_json",
  "document_count": 133,
  "min_count": 5,
  "freq": {
    "MAG": {
      "안": 29,
      "잘": 14,
      "다시": 11,
      "정말": 9,
      "못": 9,
      "다": 9,
      "먼저": 8,
      "그냥": 7,
      "늘": 7,
      "지금": 7,
      "가장": 5,
      "이제": 5
    },
    "NNB": {
      "거": 83,
      "수": 56,
      "때문": 18,
      "절": 14,
      "장": 12,
      "번": 7,
      "분": 6
    },
    "NNG": {
      "복음": 95,
      "형상": 37,
      "교사": 23,
      "사람": 70,
      "거짓": 22,
      "열심": 19,
      "황제": 11,
      "태아": 8,
      "형성": 10,
      "하나님": 40,
      "성령": 24,
      "자유": 19,
      "율법": 21,
      "사도": 20,
      "환대": 10,
      "포메이션": 6,
      "얘기": 25,
      "교회": 24,
      "인정": 17,
      "안": 24,
      "병": 9,
      "간질": 5,
      "진흙": 5,
      "환심": 5,
      "주": 22,
      "사모": 8,
      "율법주의": 6,
      "속박": 5,
      "말": 21,
      "환호": 6,
      "코로": 5,
      "승리": 11,
      "영광": 13,
      "목사": 16,
      "도": 14,
      "씨앗": 5,
      "목적": 11,
      "능력": 12,
      "규칙": 5,
      "육체": 7,
      "건강": 8,
      "말씀": 14,
      "충만": 6,
      "시험": 7,
      "육신": 5,
      "용납": 6,
      "공동체": 8,
      "주인": 8,
      "지배": 5,
      "음성": 6,
      "나라": 8,
      "삶": 11,
      "절": 11,
      "길": 9,
      "가능": 7,
      "변화": 5,
      "성도": 9,
      "단어": 8,
      "생각": 9,
      "전쟁": 5,
      "필요": 8,
      "아들": 7,
      "중요": 8,
      "이름": 8,
      "신": 6,
      "기도": 8,
      "시대": 6,
      "자녀": 6,
      "세상": 7,
      "사랑": 7,
      "오늘": 7,
      "복": 5,
      "속": 6,
      "시작": 6,
      "손": 5,
      "존재": 5,
      "눈": 5,
      "은혜": 5,
      "이야기": 5,
      "문제": 5
    },
    "NNP": {
      "그리스도": 56,
      "바울": 23,
      "예수": 35,
      "갈라디아": 7,
      "베토벤": 5,
      "셰익스피어": 5,
      "갈라디아서": 9,
      "그리스": 15,
      "일본": 6,
      "주님": 14,
      "베드로": 5,
      "누가": 10
    },
    "VA": {
      "없": 33,
      "좋": 20,
      "같": 16,
      "그렇": 16,
      "어떻": 14,
      "이렇": 10,
      "놀랍": 6,
      "높": 5,
      "많": 7
    },
    "VV": {
      "되": 136,
      "있": 102,
      "보": 40,
      "자라가": 8,
      "전하": 18,
      "대하": 22,
      "위하": 17,
      "닮": 7,
      "가지": 16,
      "받": 16,
      "나오": 15,
      "이루": 12,
      "고치": 6,
      "믿": 14,
      "알": 14,
      "주": 14,
      "내": 11,
      "자라": 6,
      "살아가": 12,
      "원하": 12,
      "세우": 9,
      "들어오": 8,
      "드러내": 7,
      "따르": 9,
      "만들": 10,
      "싸우": 6,
      "일어나": 8,
      "말미암": 6,
      "통하": 8,
      "계시": 7,
      "지키": 6,
      "끝나": 5,
      "바라보": 6,
      "알리": 5,
      "바라": 6,
      "쓰": 6,
      "듣": 6,
      "살": 6,
      "갖": 5
    }
  },
  "tfidf": {
    "MAG": {
      "안": 0.008825319537431528,
      "잘": 0.0042924130870992715,
      "다시": 0.00339787481771453,
      "정말": 0.0032794384989124946,
      "못": 0.0029293166658056887,
      "다": 0.002738892270237371,
      "먼저": 0.0026038370362717234,
      "그냥": 0.0022278352867373887,
      "늘": 0.0022278352867373887,
      "지금": 0.0021622839749092463,
      "가장": 0.0016895131728071595,
      "이제": 0.0015216068167985392
    },
    "NNB": {
      "거": 0.025447877587802824,
      "수": 0.01704199634814364,
      "때문": 0.005477784540474742,
      "절": 0.0043569673385564925,
      "장": 0.0036518563603164943,
      "번": 0.002130249543517955,
      "분": 0.0018259281801582471
    },
    "NNG": {
      "복음": 0.03210075028333603,
      "형상": 0.028888772282927928,
      "교사": 0.02388845479420175,
      "사람": 0.02130249543517955,
      "거짓": 0.015311102106131198,
      "열심": 0.01526327509940936,
      "황제": 0.012782221801881263,
      "태아": 0.012671193230410141,
      "형성": 0.012495679643100594,
      "하나님": 0.012172854534388313,
      "성령": 0.011071063897336798,
      "자유": 0.010624022823702176,
      "율법": 0.0103605134813244,
      "사도": 0.010038615690210301,
      "환대": 0.009510806688104473,
      "포메이션": 0.008763044755841998,
      "얘기": 0.00807636863207116,
      "교회": 0.00781151110881517,
      "인정": 0.0074678553143201045,
      "안": 0.007358422435027323,
      "병": 0.0071266057229212535,
      "간질": 0.006864798294021639,
      "진흙": 0.006864798294021639,
      "환심": 0.006864798294021639,
      "주": 0.006695069993913573,
      "사모": 0.006621511794529436,
      "율법주의": 0.0065646768842791215,
      "속박": 0.006525261545217301,
      "말": 0.006390748630553865,
      "환호": 0.006390647341118456,
      "코로": 0.006247839821550297,
      "승리": 0.006093525841904172,
      "영광": 0.005756984499387625,
      "목사": 0.005742378228391074,
      "도": 0.00572595274403688,
      "씨앗": 0.005470564070232601,
      "목적": 0.005245943717684231,
      "능력": 0.005187472862347066,
      "규칙": 0.004958585621326312,
      "육체": 0.004814904285323092,
      "건강": 0.004515614198700819,
      "말씀": 0.00426049908703591,
      "충만": 0.004175755119853963,
      "시험": 0.004146735413751183,
      "육신": 0.004016651341949832,
      "용납": 0.00398831600714535,
      "공동체": 0.003815231794679441,
      "주인": 0.003660111126667006,
      "지배": 0.0035643513975372764,
      "음성": 0.003554344640358157,
      "나라": 0.0034308056730828276,
      "삶": 0.0033475349969567863,
      "절": 0.0033475349969567863,
      "길": 0.0029293166658056887,
      "가능": 0.0029083025403480183,
      "변화": 0.0028766077521583085,
      "성도": 0.0027800793963118882,
      "단어": 0.0027648590752359227,
      "생각": 0.002738892270237371,
      "전쟁": 0.002694317429862781,
      "필요": 0.002623391927804929,
      "아들": 0.002589762632314924,
      "중요": 0.0025844379622627714,
      "이름": 0.0025271512978435533,
      "신": 0.002512570705237744,
      "기도": 0.002434570906877663,
      "시대": 0.002397210568375544,
      "자녀": 0.0022539270343983767,
      "세상": 0.002244543211943469,
      "사랑": 0.002130249543517955,
      "오늘": 0.002130249543517955,
      "복": 0.0021272521753205207,
      "속": 0.001982328870198102,
      "시작": 0.001909573102917762,
      "손": 0.001741098004936924,
      "존재": 0.001715086998608105,
      "눈": 0.001676885657873053,
      "은혜": 0.0016032451513881922,
      "이야기": 0.0016032451513881922,
      "문제": 0.0015794695611522206
    },
    "NNP": {
      "그리스도": 0.02056103085587918,
      "바울": 0.011645120448306144,
      "예수": 0.010811419874546232,
      "갈라디아": 0.008134141146651713,
      "베토벤": 0.007919495769006338,
      "셰익스피어": 0.007919495769006338,
      "갈라디아서": 0.0071266057229212535,
      "그리스": 0.006806697592909274,
      "일본": 0.006231770815878718,
      "주님": 0.004730636883860047,
      "베드로": 0.0037490149048474814,
      "누가": 0.00356193542677593
    },
    "VA": {
      "없": 0.01004260499087036,
      "좋": 0.006132018695856102,
      "같": 0.004869141813755326,
      "그렇": 0.004869141813755326,
      "어떻": 0.00426049908703591,
      "이렇": 0.0030432136335970784,
      "놀랍": 0.0028614238460095806,
      "높": 0.0022688991976364246,
      "많": 0.002130249543517955
    },
    "VV": {
      "되": 0.041387705416920266,
      "있": 0.0310407790626902,
      "보": 0.012172854534388313,
      "자라가": 0.0092961613104591,
      "전하": 0.007191631705126632,
      "대하": 0.00679574963542906,
      "위하": 0.005212215891477687,
      "닮": 0.0051154369048664085,
      "가지": 0.0049423633712211345,
      "받": 0.004869141813755326,
      "나오": 0.004633465660519814,
      "이루": 0.004439593083968442,
      "고치": 0.004384660204171208,
      "믿": 0.0042924130870992715,
      "알": 0.00426049908703591,
      "주": 0.00426049908703591,
      "내": 0.003977907968662309,
      "자라": 0.003944315608644327,
      "살아가": 0.0037907269467653297,
      "원하": 0.0037907269467653297,
      "세우": 0.0034862455508215956,
      "들어오": 0.00337670187080721,
      "드러내": 0.0033383278203445105,
      "따르": 0.00318161051856596,
      "만들": 0.0031589391223044412,
      "싸우": 0.0027677659743341994,
      "일어나": 0.002723594173680784,
      "말미암": 0.00247330191907652,
      "통하": 0.002452807478342441,
      "계시": 0.002244543211943469,
      "지키": 0.002219796541984221,
      "끝나": 0.00219642803362356,
      "바라보": 0.0021371612560655583,
      "알리": 0.0020449831228703144,
      "바라": 0.0019238941816658306,
      "쓰": 0.0019238941816658306,
      "듣": 0.0018812635718113127,
      "살": 0.0018259281801582471,
      "갖": 0.001780967713387965
    }
  }
}