{
  "scope": "sermon",
  "idf_scope": "church",
  "church": "H-Rg",
  "sermon": "H-Rg-0010",
  "document_unit": "sermon_json",
  "document_count": 479,
  "min_count": 5,
  "freq": {
    "MAG": {
      "더": 16,
      "이제": 15,
      "잘": 15,
      "정말": 11,
      "막": 7,
      "온전히": 5,
      "가득": 6,
      "영원히": 5,
      "다": 6
    },
    "NNB": {
      "수": 28,
      "원": 8,
      "거": 17,
      "때문": 11,
      "번": 11,
      "시": 7,
      "대로": 6,
      "줄": 9,
      "분": 9,
      "중": 7
    },
    "NNG": {
      "하나님": 108,
      "사람": 96,
      "주": 82,
      "지파": 16,
      "렙": 13,
      "땅": 52,
      "말씀": 47,
      "산지": 10,
      "인자": 13,
      "사진": 11,
      "환경": 15,
      "수장": 7,
      "만만": 5,
      "모세": 11,
      "믿음": 27,
      "여분": 5,
      "귀": 15,
      "걸음": 11,
      "영광": 18,
      "수아": 5,
      "예배": 19,
      "성도": 19,
      "마음": 19,
      "기도": 19,
      "소리": 16,
      "기업": 7,
      "족속": 7,
      "아버지": 17,
      "삶": 17,
      "시온": 6,
      "은혜": 16,
      "주소": 6,
      "문자": 5,
      "새해": 5,
      "니": 5,
      "고백": 14,
      "시작": 15,
      "기도회": 9,
      "올해": 5,
      "자손": 7,
      "날": 14,
      "그날": 9,
      "이름": 14,
      "눈": 13,
      "가운데": 14,
      "세상": 14,
      "여행": 5,
      "증거": 7,
      "위": 12,
      "발": 8,
      "약속": 10,
      "지금": 12,
      "가능": 7,
      "찬양": 11,
      "목자": 7,
      "이야기": 10,
      "힘": 11,
      "평생": 7,
      "말": 12,
      "광고": 5,
      "인생": 11,
      "손": 11,
      "민족": 8,
      "교회": 11,
      "가정": 10,
      "모습": 9,
      "생각": 11,
      "오늘": 11,
      "축복": 9,
      "특별": 6,
      "소망": 9,
      "의심": 5,
      "진행": 7,
      "나라": 9,
      "한소망": 7,
      "역사": 9,
      "행복": 7,
      "기쁨": 8,
      "안": 9,
      "집사": 7,
      "감사": 8,
      "기": 7,
      "능력": 8,
      "길": 8,
      "가족": 7,
      "전쟁": 5,
      "사랑": 8,
      "아들": 7,
      "준비": 7,
      "성령": 7,
      "주일": 6,
      "주의": 6,
      "목사": 7,
      "승리": 5,
      "사역": 6,
      "하늘": 6,
      "신앙": 6,
      "밤": 5,
      "뜻": 6,
      "경험": 5,
      "성경": 6,
      "죄": 5,
      "곳": 5,
      "자리": 5,
      "자녀": 5,
      "절": 5,
      "앞": 5
    },
    "NNP": {
      "갈": 30,
      "갈렙": 13,
      "헤브론": 7,
      "여호수아": 7,
      "이스라엘": 15,
      "여호수": 6,
      "여호": 11,
      "예수": 14,
      "여호와": 8,
      "스": 5,
      "주님": 9
    },
    "VA": {
      "크": 18,
      "많": 18,
      "없": 17,
      "힘들": 10,
      "어떻": 11,
      "그렇": 11,
      "같": 9,
      "이렇": 7,
      "좋": 7
    },
    "VV": {
      "있": 85,
      "되": 78,
      "보": 35,
      "살": 33,
      "주": 31,
      "바라": 18,
      "뒤지": 5,
      "걸어가": 11,
      "드리": 15,
      "받": 16,
      "찍": 6,
      "대하": 12,
      "기뻐하": 10,
      "믿": 13,
      "올라가": 8,
      "바라보": 10,
      "취하": 5,
      "빛나": 6,
      "원하": 10,
      "서": 10,
      "알": 11,
      "보이": 10,
      "살아가": 10,
      "통하": 9,
      "나가": 8,
      "붙들": 7,
      "부르": 8,
      "빠지": 6,
      "맡기": 6,
      "채우": 6,
      "나오": 8,
      "가지": 8,
      "위하": 8,
      "들어가": 7,
      "나아가": 6,
      "올리": 6,
      "느끼": 5,
      "보내": 6,
      "쓰": 6,
      "리": 5,
      "일어나": 6,
      "따르": 5,
      "계시": 5,
      "죽": 5
    }
  },
  "tfidf": {
    "MAG": {
      "더": 0.00405341823922633,
      "이제": 0.003961904889604394,
      "잘": 0.0038398824084148082,
      "정말": 0.003309864336926503,
      "막": 0.00289676389132713,
      "온전히": 0.002179576211623136,
      "가득": 0.0018841215214242808,
      "영원히": 0.0018191932950361348,
      "다": 0.0015042788408809297
    },
    "NNB": {
      "수": 0.0069617105917454,
      "원": 0.005050337375777823,
      "거": 0.0042444011223217734,
      "때문": 0.002935887287593386,
      "번": 0.0027521048590625433,
      "시": 0.002748265308329359,
      "대로": 0.0025383124269972085,
      "줄": 0.0024171921941101965,
      "분": 0.002318381762392174,
      "중": 0.001956332307481316
    },
    "NNG": {
      "하나님": 0.026852312282446545,
      "사람": 0.023868722028841372,
      "주": 0.020817100833968732,
      "지파": 0.016064811090891244,
      "렙": 0.014225650413129792,
      "땅": 0.013535474845590026,
      "말씀": 0.011710099155911985,
      "산지": 0.010515532383728236,
      "인자": 0.009744838206625916,
      "사진": 0.008079826550468456,
      "환경": 0.007578776283189744,
      "수장": 0.007554452839114879,
      "만만": 0.007552428910037079,
      "모세": 0.007194282580296187,
      "믿음": 0.007116560405241682,
      "여분": 0.0069173895965537495,
      "귀": 0.006044852756018098,
      "걸음": 0.00599004831032561,
      "영광": 0.005280170109079219,
      "수아": 0.005075514234887644,
      "예배": 0.005039408529844348,
      "성도": 0.005007949914799702,
      "마음": 0.004853724534666272,
      "기도": 0.004813434159081268,
      "소리": 0.004783786232168967,
      "기업": 0.004753342598677608,
      "족속": 0.004753342598677608,
      "아버지": 0.004508944474071259,
      "삶": 0.004415840426480273,
      "시온": 0.004342774082835337,
      "은혜": 0.004306220673592195,
      "주소": 0.00428103581904192,
      "문자": 0.004271651523643173,
      "새해": 0.004030284026824479,
      "니": 0.003982464184920207,
      "고백": 0.003929122590284174,
      "시작": 0.003888213380477856,
      "기도회": 0.0037701728989824102,
      "올해": 0.003767592463339637,
      "자손": 0.0037303424359936624,
      "날": 0.003690068358273465,
      "그날": 0.0036530837962932853,
      "이름": 0.003613897806932563,
      "눈": 0.0035877701734923595,
      "가운데": 0.0035246402165330787,
      "세상": 0.003509983962055503,
      "여행": 0.003455167763835775,
      "증거": 0.003447489997782716,
      "위": 0.0033891054718442532,
      "발": 0.003302550686697075,
      "약속": 0.003300217127907042,
      "지금": 0.0032567892397578034,
      "가능": 0.0032126726866699372,
      "찬양": 0.003172745009062776,
      "목자": 0.0031141315981576168,
      "이야기": 0.0030868744814866378,
      "힘": 0.0030677937058062456,
      "평생": 0.002998317641062569,
      "말": 0.002996047851050663,
      "광고": 0.002966551915862619,
      "인생": 0.002960526713094635,
      "손": 0.0029481792531493864,
      "민족": 0.0029239256673212043,
      "교회": 0.002827677043369591,
      "가정": 0.002806516135917267,
      "모습": 0.002748704489721097,
      "생각": 0.0027463771967964415,
      "오늘": 0.0027463771967964415,
      "축복": 0.002713830651046238,
      "특별": 0.002628751942387215,
      "소망": 0.0026123561657637588,
      "의심": 0.0024904302695969477,
      "진행": 0.0024901741453623024,
      "나라": 0.0024477066581942114,
      "한소망": 0.0024461103323613004,
      "역사": 0.0024222491288956103,
      "행복": 0.0023978365171446925,
      "기쁨": 0.002366682890531569,
      "안": 0.0022991326743156027,
      "집사": 0.0022266740147835907,
      "감사": 0.0022078585683029906,
      "기": 0.0022028647837222877,
      "능력": 0.0021848633969433163,
      "길": 0.00210861049044198,
      "가족": 0.0020929064765739234,
      "전쟁": 0.0020792241339597332,
      "사랑": 0.0020394188124998303,
      "아들": 0.002031832573371812,
      "준비": 0.002023280086147296,
      "성령": 0.001952232358240338,
      "주일": 0.0019085777269573633,
      "주의": 0.001880084184381402,
      "목사": 0.0018682919102867002,
      "승리": 0.0018316043392730607,
      "사역": 0.0017637815367388683,
      "하늘": 0.0017124616560068953,
      "신앙": 0.0016839096815503601,
      "밤": 0.0016828731645320426,
      "뜻": 0.001594718356270937,
      "경험": 0.0015434372407433189,
      "성경": 0.001539157680230602,
      "죄": 0.0014121272799351055,
      "곳": 0.0013400814787042665,
      "자리": 0.0013344942216333572,
      "자녀": 0.001326160139432723,
      "절": 0.0012666931997582283,
      "앞": 0.0012588000773332423
    },
    "NNP": {
      "갈": 0.028654263503680253,
      "갈렙": 0.011515983711176096,
      "헤브론": 0.007659965607069889,
      "여호수아": 0.006453593089934229,
      "이스라엘": 0.006117839191351627,
      "여호수": 0.005785105775083452,
      "여호": 0.004248442968680421,
      "예수": 0.003517304375470446,
      "여호와": 0.003334893841091466,
      "스": 0.002966551915862619,
      "주님": 0.002547176042365645
    },
    "VA": {
      "크": 0.004579139740975095,
      "많": 0.004522248482747716,
      "없": 0.004226752859273993,
      "힘들": 0.0033218688630929803,
      "어떻": 0.0028159137661708596,
      "그렇": 0.0027463771967964415,
      "같": 0.002275301856003837,
      "이렇": 0.0018220831522909652,
      "좋": 0.0018069489034662814
    },
    "VV": {
      "있": 0.021133764296369966,
      "되": 0.019393336648433616,
      "보": 0.00870213823968175,
      "살": 0.00825631457718763,
      "주": 0.007837150837346549,
      "바라": 0.004885183859636705,
      "뒤지": 0.004732086367373772,
      "걸어가": 0.004486415406991193,
      "드리": 0.004088055173618482,
      "받": 0.004019776429109081,
      "찍": 0.003846841751020408,
      "대하": 0.0035878396741267256,
      "기뻐하": 0.00358141428892141,
      "믿": 0.0032660683486511284,
      "올라가": 0.003185742559371799,
      "바라보": 0.002996217165381827,
      "취하": 0.0029562351545315705,
      "빛나": 0.0029141177704976803,
      "원하": 0.0028965015376910533,
      "서": 0.002824254559870211,
      "알": 0.0027406615045751457,
      "보이": 0.0026578639271182284,
      "살아가": 0.002538670833410821,
      "통하": 0.0023771429337626367,
      "나가": 0.002322094369567785,
      "붙들": 0.002265459522870623,
      "부르": 0.0021042147755721587,
      "빠지": 0.002068953837695518,
      "맡기": 0.0020507609887241334,
      "채우": 0.002028327556554257,
      "나오": 0.002026709119613165,
      "가지": 0.0020140801237331874,
      "위하": 0.0020140801237331874,
      "들어가": 0.0020063001695342793,
      "나아가": 0.001967251389904788,
      "올리": 0.0019376261159372045,
      "느끼": 0.0019176707136754985,
      "보내": 0.0018092204340308252,
      "쓰": 0.0016981173615770965,
      "리": 0.0015973497582907204,
      "일어나": 0.0015715892863515457,
      "따르": 0.0014330715496673422,
      "계시": 0.0014003156698852047,
      "죽": 0.0012826314001921683
    }
  }
}