{
  "scope": "sermon",
  "idf_scope": "church",
  "church": "D-Zg",
  "sermon": "D-Zg-0450",
  "document_unit": "sermon_json",
  "document_count": 664,
  "min_count": 5,
  "freq": {
    "MAG": {
      "간절히": 5
    },
    "NNB": {
      "장": 12,
      "수": 12,
      "시": 5,
      "절": 8,
      "명": 6,
      "번": 6
    },
    "NNG": {
      "기도": 103,
      "습관": 10,
      "핏방울": 5,
      "유혹": 7,
      "아버지": 20,
      "제자": 10,
      "절": 20,
      "산": 12,
      "철야": 5,
      "올리브": 5,
      "말씀": 18,
      "세례": 6,
      "나라": 15,
      "하늘": 11,
      "유대인": 5,
      "새벽": 7,
      "복음": 8,
      "시험": 6,
      "곳": 6,
      "뜻": 7,
      "가정": 5,
      "오늘": 5
    },
    "NNP": {
      "예수": 38,
      "누가복음": 11
    },
    "VA": {
      "깊": 6
    },
    "VV": {
      "되": 29,
      "원하": 12,
      "있": 21,
      "듣": 12,
      "위하": 10,
      "받": 11,
      "통하": 6,
      "이루": 6,
      "따르": 5,
      "바라": 5,
      "드리": 5
    }
  },
  "tfidf": {
    "MAG": {
      "간절히": 0.011021389689966844
    },
    "NNB": {
      "장": 0.012298457673968984,
      "수": 0.01207848797964495,
      "시": 0.00936947819414843,
      "절": 0.008539108561217786,
      "명": 0.007537844806397737,
      "번": 0.0062330624552147
    },
    "NNG": {
      "기도": 0.10305195183964064,
      "습관": 0.028148409725590753,
      "핏방울": 0.02707465284203805,
      "유혹": 0.02336296473633694,
      "아버지": 0.02334236145378947,
      "제자": 0.02064001036065549,
      "절": 0.02004020080859124,
      "산": 0.019959755887231756,
      "철야": 0.01970249240342877,
      "올리브": 0.01942492071933881,
      "말씀": 0.0180090789622673,
      "세례": 0.01601282699312819,
      "나라": 0.015866740759584417,
      "하늘": 0.012897116126381922,
      "유대인": 0.01133206005894739,
      "새벽": 0.010888025633071001,
      "복음": 0.010748682890225266,
      "시험": 0.010103835217766957,
      "곳": 0.009192649160032939,
      "뜻": 0.008282720553381254,
      "가정": 0.007092177050750569,
      "오늘": 0.005257148741831374
    },
    "NNP": {
      "예수": 0.03796203796203796,
      "누가복음": 0.032030984197640465
    },
    "VA": {
      "깊": 0.00984128203499937
    },
    "VV": {
      "되": 0.028971028971028972,
      "원하": 0.023385146322804806,
      "있": 0.02097902097902098,
      "듣": 0.013586212902190803,
      "위하": 0.011373472158669918,
      "받": 0.011005548254718904,
      "통하": 0.007935583040260296,
      "이루": 0.007230975595260975,
      "따르": 0.006310776475784964,
      "바라": 0.005393566995548011,
      "드리": 0.005209877048370084
    }
  }
}