{
  "scope": "sermon",
  "idf_scope": "church",
  "church": "O-lw",
  "sermon": "O-lw-0021",
  "document_unit": "sermon_json",
  "document_count": 81,
  "min_count": 5,
  "freq": {
    "MAG": {
      "이제": 43,
      "우쭐": 10,
      "안": 36,
      "다": 25,
      "너무": 22,
      "스스로": 13,
      "지금": 18,
      "그냥": 13,
      "잘": 13,
      "못": 11,
      "정말": 11,
      "똑같이": 7,
      "더": 8,
      "아주": 7,
      "아무리": 6,
      "아직": 5,
      "가장": 6,
      "늘": 5
    },
    "NNB": {
      "거": 103,
      "수": 39,
      "때문": 12,
      "번": 10,
      "지": 5,
      "가지": 5,
      "절": 5
    },
    "NNG": {
      "모압": 26,
      "사람": 48,
      "배반": 21,
      "하나님": 40,
      "생각": 36,
      "왕": 29,
      "앞뒤": 10,
      "노예": 10,
      "교회": 26,
      "기회": 15,
      "주상": 8,
      "악": 23,
      "기": 24,
      "분열": 7,
      "말": 22,
      "뇌물": 7,
      "아합": 11,
      "남편": 19,
      "말씀": 20,
      "개혁": 10,
      "한계": 10,
      "회개": 17,
      "사건": 17,
      "수고": 11,
      "바알": 9,
      "건축": 7,
      "조공": 5,
      "보암": 7,
      "죄": 16,
      "여로보암": 7,
      "반란": 5,
      "양육": 10,
      "형": 6,
      "이혼": 12,
      "남유": 5,
      "남쪽": 5,
      "구원": 13,
      "여호람": 6,
      "주": 13,
      "반역": 8,
      "예배": 12,
      "람": 6,
      "결혼": 11,
      "앞": 12,
      "세상": 12,
      "북쪽": 5,
      "제사장": 6,
      "결정": 7,
      "길": 11,
      "돈": 11,
      "공동체": 10,
      "뒤": 8,
      "인생": 11,
      "백성": 9,
      "가정": 10,
      "겉": 6,
      "부모": 8,
      "안": 8,
      "죄악": 6,
      "얘기": 9,
      "중요": 9,
      "분별": 6,
      "생활": 6,
      "주인": 5,
      "목장": 7,
      "아버지": 7,
      "적용": 7,
      "필요": 6,
      "모습": 6,
      "전쟁": 5,
      "인정": 6,
      "오늘": 6,
      "곳": 5,
      "삶": 5,
      "신앙": 5,
      "아내": 5,
      "속": 5,
      "시작": 5,
      "절": 5,
      "전": 5,
      "질문": 5,
      "기도": 5,
      "나라": 5,
      "날": 5,
      "마음": 5
    },
    "NNP": {
      "여호와": 22,
      "이스라엘": 19,
      "여호사밧": 7,
      "모압": 5,
      "여호": 12,
      "북이스라엘": 8,
      "다윗": 5,
      "예수": 8
    },
    "VA": {
      "이렇": 40,
      "없": 37,
      "그렇": 24,
      "같": 18,
      "어떻": 10,
      "좋": 9,
      "힘들": 8,
      "다르": 5,
      "많": 6,
      "어렵": 5
    },
    "VV": {
      "되": 98,
      "있": 72,
      "묻": 27,
      "보": 31,
      "믿": 25,
      "받": 23,
      "그러": 22,
      "눌리": 8,
      "위하": 18,
      "살": 17,
      "드리": 16,
      "바치": 7,
      "달라붙": 5,
      "알": 16,
      "듣": 14,
      "주": 14,
      "없애": 6,
      "물어보": 6,
      "행하": 10,
      "붙": 8,
      "떠나": 9,
      "바꾸": 5,
      "통하": 8,
      "나오": 8,
      "넘": 5,
      "만들": 6,
      "모르": 7,
      "보이": 6,
      "죽": 6,
      "따르": 5,
      "원하": 5,
      "지키": 5,
      "치": 5,
      "맞": 5,
      "들어가": 5,
      "만나": 5,
      "살리": 5,
      "가지": 5
    }
  },
  "tfidf": {
    "MAG": {
      "이제": 0.012024608501118568,
      "우쭐": 0.01124279889861399,
      "안": 0.010067114093959731,
      "다": 0.006991051454138702,
      "너무": 0.006152125279642058,
      "스스로": 0.006067574154572568,
      "지금": 0.0050335570469798654,
      "그냥": 0.003635346756152125,
      "잘": 0.003635346756152125,
      "못": 0.003076062639821029,
      "정말": 0.003076062639821029,
      "똑같이": 0.0027392903898832426,
      "더": 0.0022371364653243847,
      "아주": 0.0021062363950910107,
      "아무리": 0.0017192829070308245,
      "아직": 0.001680686000941397,
      "가장": 0.0016778523489932886,
      "늘": 0.0014153664605590247
    },
    "NNB": {
      "거": 0.028803131991051455,
      "수": 0.010906040268456376,
      "때문": 0.003355704697986577,
      "번": 0.002796420581655481,
      "지": 0.0026291369164542673,
      "가지": 0.0019314423329545635,
      "절": 0.0014153664605590247
    },
    "NNG": {
      "모압": 0.020661637901250172,
      "사람": 0.013422818791946308,
      "배반": 0.012396121366459288,
      "하나님": 0.011185682326621925,
      "생각": 0.010067114093959731,
      "왕": 0.009277724199235232,
      "앞뒤": 0.008680464637220938,
      "노예": 0.007366136814945391,
      "교회": 0.0073599055949069275,
      "기회": 0.00720570383032851,
      "주상": 0.007180077561360254,
      "악": 0.007179523361483452,
      "기": 0.006793759010683318,
      "분열": 0.0065131274997457834,
      "말": 0.006152125279642058,
      "뇌물": 0.006076325246054657,
      "아합": 0.005694933737003142,
      "남편": 0.005647472786018125,
      "말씀": 0.005592841163310962,
      "개혁": 0.005258273832908535,
      "한계": 0.005258273832908535,
      "회개": 0.004931100031194893,
      "사건": 0.0048713015699206694,
      "수고": 0.004854266319498529,
      "바알": 0.00473244644961768,
      "건축": 0.004719493516770647,
      "조공": 0.0046522339283898454,
      "보암": 0.004623987043284623,
      "죄": 0.004584754418748865,
      "여로보암": 0.004132040455486429,
      "반란": 0.003973391904086572,
      "양육": 0.003813389204221765,
      "형": 0.0038107802539179593,
      "이혼": 0.0037458382755565837,
      "남유": 0.0036830684074726956,
      "남쪽": 0.0036830684074726956,
      "구원": 0.0036799527974534637,
      "여호람": 0.003670878225496732,
      "주": 0.003635346756152125,
      "반역": 0.0036298201640849927,
      "예배": 0.003523524901257253,
      "람": 0.0034807294246460554,
      "결혼": 0.0034761142088171634,
      "앞": 0.003438565814061649,
      "세상": 0.003396879505341659,
      "북쪽": 0.0033710667976933196,
      "제사장": 0.0032566834638666554,
      "결정": 0.003221094496922493,
      "길": 0.003190711784890813,
      "돈": 0.0031520186628898454,
      "공동체": 0.003121531896297153,
      "뒤": 0.003090307732727301,
      "인생": 0.003076062639821029,
      "백성": 0.003063081808484465,
      "가정": 0.0029723540979042767,
      "겉": 0.0028004188405719543,
      "부모": 0.002655954232859388,
      "안": 0.002559372192892478,
      "죄악": 0.0025417767603248763,
      "얘기": 0.0025167785234899327,
      "중요": 0.0025167785234899327,
      "분별": 0.0025078796003961527,
      "생활": 0.002442073034702728,
      "주인": 0.0022064846906811497,
      "목장": 0.0020553895257333977,
      "아버지": 0.0019574944071588368,
      "적용": 0.0019574944071588368,
      "필요": 0.0019433288678102252,
      "모습": 0.0018960622957184528,
      "전쟁": 0.0018118643499593706,
      "인정": 0.0017834124587425657,
      "오늘": 0.0016778523489932886,
      "곳": 0.0016194407231751877,
      "삶": 0.001522974180268376,
      "신앙": 0.001522974180268376,
      "아내": 0.001522974180268376,
      "속": 0.0014861770489521383,
      "시작": 0.0014681353755238555,
      "절": 0.0014503235385867333,
      "전": 0.0014327357558590206,
      "질문": 0.0014153664605590247,
      "기도": 0.0013982102908277406,
      "나라": 0.0013982102908277406,
      "날": 0.0013982102908277406,
      "마음": 0.0013982102908277406
    },
    "NNP": {
      "여호와": 0.008609198368204476,
      "이스라엘": 0.006307891303041047,
      "여호사밧": 0.005156295770461773,
      "모압": 0.004340232318610469,
      "여호": 0.003934942089486556,
      "북이스라엘": 0.003435163839723405,
      "다윗": 0.002237215824236484,
      "예수": 0.0022371364653243847
    },
    "VA": {
      "이렇": 0.011185682326621925,
      "없": 0.01034675615212528,
      "그렇": 0.006711409395973154,
      "같": 0.0050335570469798654,
      "어떻": 0.002796420581655481,
      "좋": 0.0025167785234899327,
      "힘들": 0.0022923772093744327,
      "다르": 0.001723059252472897,
      "많": 0.0016778523489932886,
      "어렵": 0.0015044545679221506
    },
    "VV": {
      "되": 0.027404921700223715,
      "있": 0.020134228187919462,
      "묻": 0.01016483735776888,
      "보": 0.008668903803131992,
      "믿": 0.006991051454138702,
      "받": 0.006431767337807606,
      "그러": 0.006152125279642058,
      "눌리": 0.006037290931011282,
      "위하": 0.0050335570469798654,
      "살": 0.0047539149888143175,
      "드리": 0.004641035323477546,
      "바치": 0.004623987043284623,
      "달라붙": 0.00448754847585016,
      "알": 0.0044742729306487695,
      "듣": 0.0039149888143176735,
      "주": 0.0039149888143176735,
      "없애": 0.0036050716598033067,
      "물어보": 0.0033649695731578816,
      "행하": 0.0032388814463503754,
      "붙": 0.002935961264076404,
      "떠나": 0.0028093787066674376,
      "바꾸": 0.0024736200888393,
      "통하": 0.0022645863368944393,
      "나오": 0.0022371364653243847,
      "넘": 0.002089899666996794,
      "만들": 0.0020676711029674762,
      "모르": 0.0019815130447826345,
      "보이": 0.0016778523489932886,
      "죽": 0.0016778523489932886,
      "따르": 0.0016395592039527317,
      "원하": 0.0015607659481485766,
      "지키": 0.0015044545679221506,
      "치": 0.0015044545679221506,
      "맞": 0.0014861770489521383,
      "들어가": 0.0014681353755238555,
      "만나": 0.0014503235385867333,
      "살리": 0.0014153664605590247,
      "가지": 0.0013982102908277406
    }
  }
}