{
  "scope": "sermon",
  "idf_scope": "church",
  "church": "S-Cg",
  "sermon": "S-Cg-0177",
  "document_unit": "sermon_json",
  "document_count": 186,
  "min_count": 5,
  "freq": {
    "MAG": {
      "정말": 23,
      "다": 22,
      "이제": 17,
      "더": 16,
      "잘": 13,
      "다시": 11,
      "이미": 9,
      "지금": 9,
      "그냥": 8,
      "온전히": 5,
      "너무": 7,
      "먼저": 5,
      "너무나": 6,
      "굉장히": 5,
      "계속": 5,
      "사실": 5,
      "많이": 5
    },
    "NNB": {
      "거": 55,
      "수": 40,
      "번": 27,
      "장": 23,
      "때문": 16,
      "가지": 13,
      "뻔": 5,
      "줄": 10,
      "절": 8,
      "분": 8
    },
    "NNG": {
      "시험": 79,
      "하나님": 120,
      "사울": 60,
      "반감": 15,
      "나발": 13,
      "은혜": 55,
      "아비새": 13,
      "사람": 40,
      "주": 39,
      "반복": 15,
      "밀고": 6,
      "마음": 27,
      "모습": 23,
      "창": 8,
      "장": 23,
      "안": 24,
      "아비가일": 5,
      "말씀": 22,
      "얘기": 19,
      "정서": 7,
      "사랑": 21,
      "신뢰": 12,
      "악": 13,
      "용서": 12,
      "충동": 5,
      "고백": 16,
      "기도": 16,
      "부분": 9,
      "육신": 7,
      "옛날": 5,
      "군사": 6,
      "거부": 6,
      "내용": 8,
      "오늘": 14,
      "감사": 13,
      "임금": 6,
      "선포": 7,
      "윗이": 7,
      "방향": 5,
      "인생": 10,
      "죄": 10,
      "윗": 6,
      "길": 10,
      "죄인": 6,
      "믿음": 10,
      "다윗이": 5,
      "문제": 9,
      "십자가": 8,
      "손": 9,
      "남자": 5,
      "절": 10,
      "말": 10,
      "다윗": 5,
      "변화": 6,
      "과거": 5,
      "광야": 5,
      "아버지": 9,
      "예배": 8,
      "위기": 5,
      "주인": 5,
      "가정": 8,
      "선": 6,
      "아들": 7,
      "백성": 7,
      "속": 7,
      "이유": 6,
      "찬양": 6,
      "주님": 5,
      "가운데": 6,
      "생각": 6,
      "왕": 5,
      "복음": 5,
      "인도": 5,
      "축복": 5,
      "날": 5,
      "앞": 5,
      "삶": 5
    },
    "NNP": {
      "다윗": 43,
      "다": 13,
      "바울": 6,
      "예수": 10,
      "주님": 7
    },
    "VA": {
      "그렇": 28,
      "없": 27,
      "이렇": 23,
      "어떻": 21,
      "같": 11,
      "기쁘": 7,
      "많": 7,
      "크": 6
    },
    "VV": {
      "있": 122,
      "되": 77,
      "죽이": 27,
      "보": 32,
      "죽": 27,
      "주": 26,
      "알": 23,
      "끝나": 16,
      "살": 20,
      "만나": 15,
      "대하": 17,
      "받": 17,
      "치": 11,
      "막": 7,
      "당하": 10,
      "드리": 12,
      "원하": 11,
      "믿": 11,
      "주어지": 6,
      "이기": 7,
      "치르": 5,
      "깨닫": 8,
      "살아가": 9,
      "깨": 5,
      "보이": 9,
      "풀": 5,
      "붙잡": 6,
      "모르": 8,
      "느끼": 6,
      "살리": 6,
      "나아가": 7,
      "바라": 6,
      "나오": 7,
      "듣": 7,
      "돌아가": 5,
      "그러": 7,
      "누리": 5,
      "일어나": 6,
      "지": 5,
      "나가": 5,
      "위하": 6,
      "만들": 5,
      "지나": 5
    }
  },
  "tfidf": {
    "MAG": {
      "정말": 0.006815736983522561,
      "다": 0.006347374495095211,
      "이제": 0.0049310885843634016,
      "더": 0.004616272360069244,
      "잘": 0.0038318211287279727,
      "다시": 0.0032423101858467464,
      "이미": 0.0030015618045547716,
      "지금": 0.0026957201078128645,
      "그냥": 0.0025145875599582846,
      "온전히": 0.0022889753573473947,
      "너무": 0.0021079225842749053,
      "먼저": 0.002000752351984991,
      "너무나": 0.0019582957686619528,
      "굉장히": 0.001732069670314702,
      "계속": 0.0016948396011342737,
      "사실": 0.001667534335863762,
      "많이": 0.0016407363185917834
    },
    "NNB": {
      "거": 0.01603906622841731,
      "수": 0.01154068090017311,
      "번": 0.007789959607616849,
      "장": 0.006815736983522561,
      "때문": 0.004616272360069244,
      "가지": 0.004064334627967321,
      "뻔": 0.003944894771188844,
      "줄": 0.0030437359615717178,
      "절": 0.002345465341594001,
      "분": 0.0023329550877697904
    },
    "NNG": {
      "시험": 0.05285855836776941,
      "하나님": 0.03462204270051933,
      "사울": 0.033126725389237326,
      "반감": 0.023966942165152803,
      "나발": 0.016072585136004198,
      "은혜": 0.015868436237738027,
      "아비새": 0.015129974758724402,
      "사람": 0.01154068090017311,
      "주": 0.011252163877668782,
      "반복": 0.009247392042552594,
      "밀고": 0.008386868301906571,
      "마음": 0.007831728928106579,
      "모습": 0.007466460556244126,
      "창": 0.007247700319668253,
      "장": 0.007114029516942101,
      "안": 0.00707413131457472,
      "아비가일": 0.006404138989651661,
      "말씀": 0.006347374495095211,
      "얘기": 0.006302475702692542,
      "정서": 0.0061660079358183744,
      "사랑": 0.006058857472590883,
      "신뢰": 0.00595585381536435,
      "악": 0.005915443585418876,
      "용서": 0.0055607702374044395,
      "충동": 0.005181839710385643,
      "고백": 0.005083484832921007,
      "기도": 0.004616272360069244,
      "부분": 0.004221998233640641,
      "육신": 0.004185106386169764,
      "옛날": 0.004181915906923518,
      "군사": 0.004158916134504602,
      "거부": 0.004121686696730285,
      "내용": 0.004101007087365444,
      "오늘": 0.004039238315060588,
      "감사": 0.003914713370796252,
      "임금": 0.003881346630623737,
      "선포": 0.0038647846287443548,
      "윗이": 0.0038380343150541804,
      "방향": 0.0035630532330655283,
      "인생": 0.0033896792022685474,
      "죄": 0.0033896792022685474,
      "윗": 0.003335909158079199,
      "길": 0.003281472637183567,
      "죄인": 0.003244777478646846,
      "믿음": 0.0031096855809486664,
      "다윗이": 0.003035161903937529,
      "문제": 0.0030015618045547716,
      "십자가": 0.002992809425790871,
      "손": 0.0029374436529929293,
      "남자": 0.0029232775497167055,
      "절": 0.002900640343743178,
      "말": 0.0028851702250432777,
      "다윗": 0.0028194496506614704,
      "변화": 0.002763496183424612,
      "과거": 0.0027605604491031106,
      "광야": 0.0027605604491031106,
      "아버지": 0.0026670275152914373,
      "예배": 0.00265367398008107,
      "위기": 0.0026495375969159667,
      "주인": 0.002631836944013753,
      "가정": 0.002487748464758933,
      "선": 0.002442285720570484,
      "아들": 0.002347210300761825,
      "백성": 0.002272401038856908,
      "속": 0.002212109422570766,
      "이유": 0.00212434329643819,
      "찬양": 0.0018459134038045111,
      "주님": 0.0017800004949372068,
      "가운데": 0.00176853282864368,
      "생각": 0.0017590990061955008,
      "왕": 0.0017415292787194322,
      "복음": 0.0016319131405516274,
      "인도": 0.0016319131405516274,
      "축복": 0.0015885890102878151,
      "날": 0.0015548427904743332,
      "앞": 0.0014896301003877103,
      "삶": 0.0014580969298561193
    },
    "NNP": {
      "다윗": 0.019102628848497994,
      "다": 0.0054776433644131515,
      "바울": 0.0036144960596590668,
      "예수": 0.002900640343743178,
      "주님": 0.0021535656377719295
    },
    "VA": {
      "그렇": 0.008078476630121177,
      "없": 0.007789959607616849,
      "이렇": 0.006635891517599538,
      "어떻": 0.006091344721860673,
      "같": 0.003207813245683462,
      "기쁘": 0.002865686621573913,
      "많": 0.0020304482406202245,
      "크": 0.0017971467385419096
    },
    "VV": {
      "있": 0.03519907674552799,
      "되": 0.022215810732833238,
      "죽이": 0.01086564372977032,
      "보": 0.009232544720138488,
      "죽": 0.00800108254587431,
      "주": 0.0075014425851125215,
      "알": 0.006635891517599538,
      "끝나": 0.006438899988012042,
      "살": 0.005801280687486356,
      "만나": 0.005224587836158296,
      "대하": 0.0051467184453440635,
      "받": 0.0049310885843634016,
      "치": 0.004115112960462448,
      "막": 0.0037093526356823526,
      "당하": 0.00350210265447104,
      "드리": 0.003462204270051933,
      "원하": 0.003366090836693821,
      "믿": 0.0031907043781174956,
      "주어지": 0.0030960023549294925,
      "이기": 0.0030369433315048243,
      "치르": 0.0030120800497158893,
      "깨닫": 0.002992809425790871,
      "살아가": 0.0027837506805425617,
      "깨": 0.0027605604491031106,
      "보이": 0.0026386485092932516,
      "풀": 0.0024975460855803833,
      "붙잡": 0.0024846821775958085,
      "모르": 0.0023706911247034996,
      "느끼": 0.0023604861507195685,
      "살리": 0.002347220935349282,
      "나아가": 0.002272401038856908,
      "바라": 0.002232197681901816,
      "나오": 0.0020743547341155622,
      "듣": 0.002052282173894751,
      "돌아가": 0.0020469190154099384,
      "그러": 0.0020413357017985668,
      "누리": 0.0018705058911192944,
      "일어나": 0.0018067907865213474,
      "지": 0.0017996278060390225,
      "나가": 0.0017800004949372068,
      "위하": 0.0017311021350259665,
      "만들": 0.0017133345353943163,
      "지나": 0.0016856802998090306
    }
  }
}