{
  "scope": "sermon",
  "idf_scope": "church",
  "church": "O-Sg",
  "sermon": "O-Sg-0739",
  "document_unit": "sermon_json",
  "document_count": 819,
  "min_count": 5,
  "freq": {
    "MAG": {
      "이제": 60,
      "정말": 22,
      "지금": 15,
      "다시": 14,
      "더": 14,
      "계속": 10,
      "가장": 11,
      "그냥": 10,
      "다": 12,
      "때로": 7,
      "안": 9,
      "갑자기": 5,
      "잘": 8,
      "굉장히": 5,
      "많이": 7,
      "막": 5,
      "너무": 5
    },
    "NNB": {
      "수": 58,
      "거": 29,
      "명": 19,
      "번": 21,
      "절": 15,
      "달": 5,
      "가지": 8,
      "분": 9
    },
    "NNG": {
      "모세": 68,
      "사람": 97,
      "이드로": 10,
      "장인": 10,
      "삶": 48,
      "산양": 7,
      "하나님": 45,
      "백성": 24,
      "말씀": 40,
      "열정": 12,
      "목적지": 9,
      "민원": 5,
      "사랑": 31,
      "촌장": 5,
      "눈빛": 6,
      "생각": 26,
      "말": 26,
      "길": 22,
      "처리": 7,
      "조언": 6,
      "리더십": 8,
      "마음": 24,
      "지혜": 13,
      "가운데": 24,
      "물고기": 7,
      "그물": 5,
      "밤": 11,
      "이야기": 18,
      "순간": 14,
      "시골": 5,
      "시작": 20,
      "풀": 5,
      "중간": 7,
      "오늘": 19,
      "무리": 7,
      "중요": 16,
      "조직": 5,
      "성실": 5,
      "아침": 8,
      "지도자": 8,
      "방향": 7,
      "가족": 10,
      "계속": 11,
      "얘기": 11,
      "앞": 15,
      "영화": 5,
      "일상": 5,
      "자리": 11,
      "집": 9,
      "아내": 6,
      "모습": 10,
      "뜻": 9,
      "날": 9,
      "방법": 6,
      "목소리": 5,
      "성경": 9,
      "장면": 5,
      "복": 5,
      "본문": 7,
      "자녀": 6,
      "기도": 8,
      "이후": 5,
      "주": 7,
      "문제": 5,
      "힘": 5,
      "존재": 5,
      "기록": 5,
      "필요": 5,
      "절": 6
    },
    "NNP": {
      "이집트": 10,
      "베드로": 10,
      "예수": 17,
      "이스라엘": 6,
      "그리스도": 8
    },
    "VA": {
      "그렇": 37,
      "낫": 9,
      "이렇": 21,
      "좋": 17,
      "옳": 7,
      "없": 14,
      "올바르": 5,
      "많": 10,
      "같": 5
    },
    "VV": {
      "있": 141,
      "되": 69,
      "멈추": 22,
      "바라": 21,
      "달려가": 10,
      "가지": 22,
      "달리": 10,
      "새": 5,
      "나누": 16,
      "보": 20,
      "향하": 15,
      "위하": 17,
      "나오": 14,
      "보내": 11,
      "지치": 5,
      "나아가": 11,
      "만나": 11,
      "돌이키": 6,
      "돌아보": 6,
      "원하": 12,
      "먹": 8,
      "알": 12,
      "듣": 11,
      "내리": 6,
      "열": 6,
      "일어나": 10,
      "그러": 10,
      "살아가": 9,
      "이끌": 5,
      "잡": 5,
      "돌아가": 6,
      "지나": 6,
      "읽": 9,
      "찾아오": 5,
      "행하": 6,
      "통하": 8,
      "드리": 7,
      "세우": 5,
      "살": 7,
      "주": 7,
      "들어가": 5,
      "만들": 5,
      "따르": 5,
      "죽": 5,
      "모르": 5
    }
  },
  "tfidf": {
    "MAG": {
      "이제": 0.02108829556797053,
      "정말": 0.011011149976263773,
      "지금": 0.005910952668378928,
      "다시": 0.0048786949928898565,
      "더": 0.004737839835654219,
      "계속": 0.004527886515691373,
      "가장": 0.004286614513512078,
      "그냥": 0.004147466094476609,
      "다": 0.0041158837031750935,
      "때로": 0.0038444710111438614,
      "안": 0.0034006130533910943,
      "갑자기": 0.0032298472354691434,
      "잘": 0.0028991213292851904,
      "굉장히": 0.0028722030217832387,
      "많이": 0.0027584445785768332,
      "막": 0.002726579748821787,
      "너무": 0.0023264862435318405
    },
    "NNB": {
      "수": 0.019085225403093122,
      "거": 0.00999540585445102,
      "명": 0.009731774026169692,
      "번": 0.006969410281316306,
      "절": 0.0051953495364259975,
      "달": 0.004121911242483553,
      "가지": 0.0030868384143915594,
      "분": 0.0030494723230421986
    },
    "NNG": {
      "모세": 0.05693558700584579,
      "사람": 0.031918394208621255,
      "이드로": 0.02080621908239029,
      "장인": 0.016456907335163175,
      "삶": 0.01638335865425045,
      "산양": 0.016160941137837604,
      "하나님": 0.014807502467917079,
      "백성": 0.013218739646464302,
      "말씀": 0.013194366616065179,
      "열정": 0.011671131882139916,
      "목적지": 0.011557675766499445,
      "민원": 0.011543529384169717,
      "사랑": 0.010935648429808851,
      "촌장": 0.010876426540951282,
      "눈빛": 0.009407434079154705,
      "생각": 0.008713397049632483,
      "말": 0.008586803678958766,
      "길": 0.008562622104351823,
      "처리": 0.008326659574285418,
      "조언": 0.008317466493172396,
      "리더십": 0.008306488841481429,
      "마음": 0.008211697930111901,
      "지혜": 0.008197360814203362,
      "가운데": 0.008082474970897844,
      "물고기": 0.008004733415474589,
      "그물": 0.007674863281564455,
      "밤": 0.007640574594886202,
      "이야기": 0.007344841205108745,
      "순간": 0.006885734579040966,
      "시골": 0.006742985237930363,
      "시작": 0.006735395809081538,
      "풀": 0.0065740906113096265,
      "중간": 0.006424897631132352,
      "오늘": 0.006321056083157233,
      "무리": 0.006231492675284592,
      "중요": 0.006143243855223399,
      "조직": 0.0059752663645155964,
      "성실": 0.0059204186839173865,
      "아침": 0.0058558931405531915,
      "지도자": 0.005834137273886805,
      "방향": 0.005695964673247267,
      "가족": 0.005636236431850206,
      "계속": 0.005520470530611705,
      "얘기": 0.005446598339778116,
      "앞": 0.005246366364316728,
      "영화": 0.004713914534056775,
      "일상": 0.004713914534056775,
      "자리": 0.004696395787440744,
      "집": 0.004673478333983686,
      "아내": 0.004006183082411119,
      "모습": 0.003979984533078133,
      "뜻": 0.003966643704136442,
      "날": 0.0037515227259331692,
      "방법": 0.0036272192512988802,
      "목소리": 0.0035865009094223025,
      "성경": 0.003269515555706112,
      "장면": 0.003142829361299396,
      "복": 0.0030319780903669004,
      "본문": 0.0028420866616911686,
      "자녀": 0.0027414334570734773,
      "기도": 0.0026679971653828425,
      "이후": 0.0024890757032967723,
      "주": 0.0023602659717448502,
      "문제": 0.0023234534720703573,
      "힘": 0.002314388556290546,
      "존재": 0.0022465019844224547,
      "기록": 0.002217837878718828,
      "필요": 0.0020737330472383043,
      "절": 0.002013238047540636
    },
    "NNP": {
      "이집트": 0.010488699451165708,
      "베드로": 0.007836223005820066,
      "예수": 0.0056144485593191944,
      "이스라엘": 0.003367062730803079,
      "그리스도": 0.003105983552474034
    },
    "VA": {
      "그렇": 0.012294421850468895,
      "낫": 0.0072456490168413025,
      "이렇": 0.006918599994902868,
      "좋": 0.006415473574069709,
      "옳": 0.005683745072849818,
      "없": 0.004618028315622812,
      "올바르": 0.0045772468823644195,
      "많": 0.003380045221482363,
      "같": 0.0016982903570437037
    },
    "VV": {
      "있": 0.04639684106614018,
      "되": 0.022704837117472853,
      "멈추": 0.016997784745006655,
      "바라": 0.009411062106827265,
      "달려가": 0.008772225150835972,
      "가지": 0.007445176884599488,
      "달리": 0.007333548591366592,
      "새": 0.006931222077643663,
      "나누": 0.00671145940886263,
      "보": 0.006589142852288446,
      "향하": 0.006205604076115858,
      "위하": 0.005655681758614367,
      "나오": 0.00493264617153172,
      "보내": 0.004879243333181422,
      "지치": 0.004848848972458939,
      "나아가": 0.004643295396777456,
      "만나": 0.0046025270140641235,
      "돌이키": 0.004571918645421396,
      "돌아보": 0.0045363441034615174,
      "원하": 0.004316837730011773,
      "먹": 0.004120088729536434,
      "알": 0.0040166657364330526,
      "듣": 0.0038851384107562287,
      "내리": 0.003649591543519117,
      "열": 0.0036439746587565674,
      "일어나": 0.003579791669938019,
      "그러": 0.0035276285257447907,
      "살아가": 0.0034942314965332884,
      "이끌": 0.003460846123662885,
      "잡": 0.003332880179203055,
      "돌아가": 0.0032765466634281162,
      "지나": 0.003031625343250468,
      "읽": 0.003023542822245421,
      "찾아오": 0.002932507920842198,
      "행하": 0.0027556886356983282,
      "통하": 0.0026582533730743554,
      "드리": 0.002505854168956613,
      "세우": 0.0024073668555063114,
      "살": 0.0023631470093597134,
      "주": 0.0023459145902856686,
      "들어가": 0.0023234534720703573,
      "만들": 0.00212395426838119,
      "따르": 0.0020099051032801715,
      "죽": 0.002004904254287252,
      "모르": 0.0019974313661093954
    }
  }
}